pyarmor_runtime_000000/__init__.py
qda_my_pkg/__init__.py
qda_my_pkg/my_module.py
qda_my_pkg-1.0.2.dist-info/LICENSE
qda_my_pkg-1.0.2.dist-info/METADATA
qda_my_pkg-1.0.2.dist-info/WHEEL
qda_my_pkg-1.0.2.dist-info/top_level.txt
qda_my_pkg-1.0.2.dist-info/RECORD
